siddharthaimageproc/__init__.py
siddharthaimageproc-0.0.1.dist-info/LICENCE.txt
siddharthaimageproc-0.0.1.dist-info/METADATA
siddharthaimageproc-0.0.1.dist-info/WHEEL
siddharthaimageproc-0.0.1.dist-info/top_level.txt
siddharthaimageproc-0.0.1.dist-info/RECORD
