Metadata-Version: 2.1
Name: siddharthaimageproc
Version: 0.0.1
Summary: A basic image processing package
Home-page: 
Author: Siddhartha
Author-email: chappidisiddhartha59736@gmail.com
License: MIT
Keywords: calculator
Classifier: Development Status :: 5 - Production/Stable
Classifier: Intended Audience :: Education
Classifier: Operating System :: Microsoft :: Windows :: Windows 10
Classifier: License :: OSI Approved :: MIT License
Classifier: Programming Language :: Python :: 3
License-File: LICENCE.txt
Requires-Dist: numpy
Requires-Dist: matplotlib
Requires-Dist: opencv-python
